gatcontroller.py
iota_command_maker.py
lattu.py
lattu-0.2.dist-info/METADATA
lattu-0.2.dist-info/RECORD
lattu-0.2.dist-info/WHEEL
lattu-0.2.dist-info/top_level.txt
