Metadata-Version: 2.1
Name: lattu
Version: 0.2
Summary: straightforward way to control BLE controlled smart bulbs
Home-page: https://github.com/pycampers/lattu
Author: infogeek
Author-email: pycampers@gmail.com
License: MIT
Platform: UNKNOWN
Classifier: License :: OSI Approved :: MIT License
Classifier: Programming Language :: Python
Classifier: Programming Language :: Python :: 3
Classifier: Programming Language :: Python :: 3.6
Classifier: Programming Language :: Python :: Implementation :: CPython
Classifier: Programming Language :: Python :: Implementation :: PyPy
Requires-Python: >=3
Requires-Dist: pexpect
